MANIFEST.in
README.md
setup.cfg
setup.py
src/pata_password_cracker/__init__.py
src/pata_password_cracker/__main__.py
src/pata_password_cracker/categories.py
src/pata_password_cracker/gen_logo.py
src/pata_password_cracker/input.py
src/pata_password_cracker/output.py
src/pata_password_cracker.egg-info/PKG-INFO
src/pata_password_cracker.egg-info/SOURCES.txt
src/pata_password_cracker.egg-info/dependency_links.txt
src/pata_password_cracker.egg-info/entry_points.txt
src/pata_password_cracker.egg-info/requires.txt
src/pata_password_cracker.egg-info/top_level.txt
src/pata_password_cracker/encryption/__init__.py
src/pata_password_cracker/encryption/bcrypt/__init__.py
src/pata_password_cracker/encryption/bcrypt/__main__.py
src/pata_password_cracker/encryption/md5/__init__.py
src/pata_password_cracker/encryption/md5/__main__.py
src/pata_password_cracker/encryption/sha1/__init__.py
src/pata_password_cracker/encryption/sha1/__main__.py
src/pata_password_cracker/encryption/sha224/__init__.py
src/pata_password_cracker/encryption/sha224/__main__.py
src/pata_password_cracker/encryption/sha256/__init__.py
src/pata_password_cracker/encryption/sha256/__main__.py
src/pata_password_cracker/encryption/sha384/__init__.py
src/pata_password_cracker/encryption/sha384/__main__.py
src/pata_password_cracker/encryption/sha512/__init__.py
src/pata_password_cracker/encryption/sha512/__main__.py
src/pata_password_cracker/generators/__init__.py
src/pata_password_cracker/generators/date_name_mixin.py
src/pata_password_cracker/generators/gen_password.py
src/pata_password_cracker/generators/core_bio/__init__.py
src/pata_password_cracker/generators/core_bio/__main__.py
src/pata_password_cracker/generators/family/__init__.py
src/pata_password_cracker/generators/family/__main__.py
src/pata_password_cracker/generators/free_data/__init__.py
src/pata_password_cracker/generators/free_data/__main__.py
src/pata_password_cracker/substitutors/__init__.py
src/pata_password_cracker/substitutors/common/__init__.py
src/pata_password_cracker/substitutors/simple/__init__.py
src/pata_password_cracker/substitutors/simplerandom/__init__.py