Metadata-Version: 1.2
Name: pata-password-cracker
Version: 2.0.0
Summary: Pataphysical passwork cracker using personal data
Home-page: https://github.com/LesPatamechanix/pata-password-cracker
Maintainer: rpigu-i
License: MIT
Platform: UNKNOWN
